odoo/addons/repair_type/README.rst
odoo/addons/repair_type/__init__.py
odoo/addons/repair_type/__manifest__.py
odoo/addons/repair_type/i18n/hr.po
odoo/addons/repair_type/i18n/repair_type.pot
odoo/addons/repair_type/models/__init__.py
odoo/addons/repair_type/models/repair.py
odoo/addons/repair_type/models/repair_type.py
odoo/addons/repair_type/readme/CONFIGURE.rst
odoo/addons/repair_type/readme/CONTRIBUTORS.rst
odoo/addons/repair_type/readme/DESCRIPTION.rst
odoo/addons/repair_type/readme/ROADMAP.rst
odoo/addons/repair_type/readme/USAGE.rst
odoo/addons/repair_type/security/ir.model.access.csv
odoo/addons/repair_type/static/description/icon.png
odoo/addons/repair_type/static/description/index.html
odoo/addons/repair_type/tests/__init__.py
odoo/addons/repair_type/tests/test_repair_type.py
odoo/addons/repair_type/views/repair.xml
odoo/addons/repair_type/views/repair_type.xml
odoo14_addon_repair_type-14.0.1.0.2.dist-info/METADATA
odoo14_addon_repair_type-14.0.1.0.2.dist-info/WHEEL
odoo14_addon_repair_type-14.0.1.0.2.dist-info/top_level.txt
odoo14_addon_repair_type-14.0.1.0.2.dist-info/RECORD
